[{"code": "A10000", "price": 128280}, {"code": "A10030", "price": 307060}, {"code": "A10079", "price": 1317800}, {"code": "A20301", "price": 504090}, {"code": "A52201", "price": 669530}, {"code": "A10239", "price": 233060}, {"code": "A90230", "price": 61220}, {"code": "A10771", "price": 87980}, {"code": "A99877", "price": 716650}, {"code": "A99031", "price": 19150}, {"code": "A32526", "price": 725420}, {"code": "A35580", "price": 130370}, {"code": "A23985", "price": 246810}, {"code": "A94873", "price": 23580}, {"code": "A94220", "price": 365220}, {"code": "A99912", "price": 16050}, {"code": "A77553", "price": 20750}]