[{"code": "A10000", "price": 68910}, {"code": "A10030", "price": 171940}, {"code": "A10079", "price": 456030}, {"code": "A20301", "price": 255760}, {"code": "A52201", "price": 867690}, {"code": "A10239", "price": 100210}, {"code": "A90230", "price": 40970}, {"code": "A10771", "price": 92790}, {"code": "A99877", "price": 519090}, {"code": "A99031", "price": 7330}, {"code": "A32526", "price": 213220}, {"code": "A35580", "price": 156340}, {"code": "A23985", "price": 241430}, {"code": "A94873", "price": 14480}, {"code": "A94220", "price": 223550}, {"code": "A99912", "price": 10800}, {"code": "A77553", "price": 6340}]