[{"code": "A10000", "price": 118300}, {"code": "A10030", "price": 173040}, {"code": "A10079", "price": 1418020}, {"code": "A20301", "price": 385310}, {"code": "A52201", "price": 688770}, {"code": "A10239", "price": 236510}, {"code": "A90230", "price": 63220}, {"code": "A10771", "price": 140710}, {"code": "A99877", "price": 803410}, {"code": "A99031", "price": 16400}, {"code": "A32526", "price": 860910}, {"code": "A35580", "price": 98450}, {"code": "A23985", "price": 255840}, {"code": "A94873", "price": 33470}, {"code": "A94220", "price": 422480}, {"code": "A99912", "price": 16080}, {"code": "A77553", "price": 22590}]