[{"code": "A10000", "price": 198470}, {"code": "A10030", "price": 450320}, {"code": "A10079", "price": 4345580}, {"code": "A20301", "price": 1092560}, {"code": "A52201", "price": 1162300}, {"code": "A10239", "price": 274800}, {"code": "A90230", "price": 110990}, {"code": "A10771", "price": 285800}, {"code": "A99877", "price": 916500}, {"code": "A99031", "price": 42630}, {"code": "A32526", "price": 1154830}, {"code": "A35580", "price": 173450}, {"code": "A23985", "price": 329680}, {"code": "A94873", "price": 43550}, {"code": "A94220", "price": 904000}, {"code": "A99912", "price": 15800}, {"code": "A77553", "price": 50570}]