[{"code": "A10000", "price": 129140}, {"code": "A10030", "price": 385050}, {"code": "A10079", "price": 2233590}, {"code": "A20301", "price": 659000}, {"code": "A52201", "price": 847700}, {"code": "A10239", "price": 205580}, {"code": "A90230", "price": 91450}, {"code": "A10771", "price": 252280}, {"code": "A99877", "price": 620760}, {"code": "A99031", "price": 29820}, {"code": "A32526", "price": 796030}, {"code": "A35580", "price": 119980}, {"code": "A23985", "price": 244000}, {"code": "A94873", "price": 48440}, {"code": "A94220", "price": 461630}, {"code": "A99912", "price": 11120}, {"code": "A77553", "price": 21890}]