[{"code": "A10000", "price": 129520}, {"code": "A10030", "price": 274840}, {"code": "A10079", "price": 1210560}, {"code": "A20301", "price": 488750}, {"code": "A52201", "price": 636110}, {"code": "A10239", "price": 219680}, {"code": "A90230", "price": 59820}, {"code": "A10771", "price": 96440}, {"code": "A99877", "price": 488350}, {"code": "A99031", "price": 14140}, {"code": "A32526", "price": 505650}, {"code": "A35580", "price": 149730}, {"code": "A23985", "price": 201940}, {"code": "A94873", "price": 22520}, {"code": "A94220", "price": 272840}, {"code": "A99912", "price": 15550}, {"code": "A77553", "price": 9490}]