[{"code": "A10000", "price": 121700}, {"code": "A10030", "price": 455720}, {"code": "A10079", "price": 1859880}, {"code": "A20301", "price": 661820}, {"code": "A52201", "price": 770800}, {"code": "A10239", "price": 195630}, {"code": "A90230", "price": 86900}, {"code": "A10771", "price": 248710}, {"code": "A99877", "price": 578500}, {"code": "A99031", "price": 28110}, {"code": "A32526", "price": 868750}, {"code": "A35580", "price": 98920}, {"code": "A23985", "price": 248100}, {"code": "A94873", "price": 42230}, {"code": "A94220", "price": 446930}, {"code": "A99912", "price": 12900}, {"code": "A77553", "price": 21580}]