[{"code": "A10000", "price": 129280}, {"code": "A10030", "price": 182480}, {"code": "A10079", "price": 1618780}, {"code": "A20301", "price": 341510}, {"code": "A52201", "price": 960660}, {"code": "A10239", "price": 149970}, {"code": "A90230", "price": 54000}, {"code": "A10771", "price": 176710}, {"code": "A99877", "price": 738680}, {"code": "A99031", "price": 27060}, {"code": "A32526", "price": 804870}, {"code": "A35580", "price": 72380}, {"code": "A23985", "price": 194430}, {"code": "A94873", "price": 47060}, {"code": "A94220", "price": 534310}, {"code": "A99912", "price": 14220}, {"code": "A77553", "price": 24700}]